<sentence_list>
	<dependency>(NP_AJT)--down--(VNP_MOD)</dependency>
	<total>3</total>
	<sent_item id="M_T3695" total_morp="45" total_word="23">
		<sent>이 곡은 밴드의 기타리스트이자 메인 작곡가인 노엘_갤러거에 의해 씌여졌는데, 곧 플래티넘 앨범이 되어 밴드의 영국 음반 차트 1위를 차지한 두 번째 싱글이 되었다.</sent>
		<sbj type="PS_NAME" weight="0.48" label="NP_AJT" josa="에">노엘_갤러거</sbj>
		<obj type="CV_OCCUPATION" weight="3.04" label="VNP_MOD" josa="">작곡가</obj>
		<gold>occupation</gold>
		<mln_predict conf="0.431">currentMember</mln_predict>
		<cnn_predict conf="0.779">occupation</cnn_predict>
		<gsdp>(NP_AJT)--down--(VNP_MOD)</gsdp>
		<gsdp_lemma></gsdp_lemma>
		<head>되었다.</head>
		<cluster>47</cluster>
		<comment></comment>
	</sent_item>
	<sent_item id="M_T2835" total_morp="28" total_word="11">
		<sent>라쿠텐의 포수인 시마_모토히로는 마쓰이의 투구를 다나카 마사히로와 비교하면서 다음과 같이 말했다.</sent>
		<sbj type="PS_NAME" weight="0.20" label="NP_AJT" josa="는">시마_모토히로</sbj>
		<obj type="CV_POSITION" weight="3.17" label="VNP_MOD" josa="">포수</obj>
		<gold>position</gold>
		<mln_predict conf="0.809">position</mln_predict>
		<cnn_predict conf="0.631">position</cnn_predict>
		<gsdp>(NP_AJT)--down--(VNP_MOD)</gsdp>
		<gsdp_lemma></gsdp_lemma>
		<head>말했다.</head>
		<cluster>24</cluster>
		<comment></comment>
	</sent_item>
	<sent_item id="M_T1423" total_morp="28" total_word="12">
		<sent>같은 세대 발라드 가수들인 박정운, 조정현, 최용준, 김민우, 박정수_(가수)와 절친한 친구 관계이다.</sent>
		<sbj type="PS_NAME" weight="0.48" label="NP_AJT" josa="와">박정수_(가수)</sbj>
		<obj type="CV_OCCUPATION" weight="3.04" label="VNP_MOD" josa="">가수</obj>
		<gold>occupation</gold>
		<mln_predict conf="1.000">occupation</mln_predict>
		<cnn_predict conf="0.978">occupation</cnn_predict>
		<gsdp>(NP_AJT)--down--(VNP_MOD)</gsdp>
		<gsdp_lemma></gsdp_lemma>
		<head>관계이다.</head>
		<cluster>6</cluster>
		<comment></comment>
	</sent_item>
</sentence_list>
