<sentence_list>
	<dependency>(NP)--up--NP_AJT--down--(NP_AJT)</dependency>
	<total>1</total>
	<sent_item id="M_T2988" total_morp="48" total_word="23">
		<sent>당시 3루수는 가케후 마사유키, 유격수에 마유미_아키노부, 2루수에 나카무라 가쓰히로, 사카키바라 요시유키, 도쿄 야쿠르트 스왈로스로부터 영입한 데이브 힐튼이 배치돼 있어 오카다가 들어갈 장소는 없었다.</sent>
		<sbj type="PS_NAME" weight="0.20" label="NP" josa="">마유미_아키노부</sbj>
		<obj type="CV_POSITION" weight="3.17" label="NP_AJT" josa="에">유격수</obj>
		<gold>position</gold>
		<mln_predict conf="0.551">position</mln_predict>
		<cnn_predict conf="0.567">team</cnn_predict>
		<gsdp>(NP)--up--NP_AJT--down--(NP_AJT)</gsdp>
		<gsdp_lemma>가쓰히로,</gsdp_lemma>
		<head>없었다.</head>
		<cluster>9</cluster>
		<comment></comment>
	</sent_item>
</sentence_list>
