<sentence_list>
	<dependency>(NP_PRN)--up--X--up--NP--down--(NP)</dependency>
	<total>1</total>
	<sent_item id="M_T833" total_morp="27" total_word="14">
		<sent>2016년 KBS2 해피선데이- 슈퍼맨이_돌아왔다 - 최초로 외동딸 오서흔 공개와 동시에 공동육아구역 OGG 멤버 합류</sent>
		<sbj type="OGG_SPORTS" weight="-0.69" label="NP_PRN" josa="">슈퍼맨이_돌아왔다</sbj>
		<obj type="AFW_VIDEO" weight="-0.16" label="NP" josa="">해피선데이</obj>
		<gold>related</gold>
		<mln_predict conf="0.442">team</mln_predict>
		<cnn_predict conf="0.493">starring</cnn_predict>
		<gsdp>(NP_PRN)--up--X--up--NP--down--(NP)</gsdp>
		<gsdp_lemma>---합류</gsdp_lemma>
		<head>합류</head>
		<cluster>32</cluster>
		<comment></comment>
	</sent_item>
</sentence_list>
