<sentence_list>
	<dependency>(NP_MOD)--down--NP--down--VP_MOD--down--NP_AJT--down--NP--down--(NP)</dependency>
	<total>2</total>
	<sent_item id="M_T2386" total_morp="25" total_word="11">
		<sent>아쓰 역은 일본 야마구치_현 미네 시에 위치한 서일본 여객철도 미네_선의 철도역이다.</sent>
		<sbj type="" weight="0.00" label="NP_MOD" josa="의">미네_선</sbj>
		<obj type="LCP_CITY" weight="0.18" label="NP" josa="">야마구치_현</obj>
		<gold>routeStart</gold>
		<mln_predict conf="1.000">routeStart</mln_predict>
		<cnn_predict conf="0.670">routeStart</cnn_predict>
		<gsdp>(NP_MOD)--down--NP--down--VP_MOD--down--NP_AJT--down--NP--down--(NP)</gsdp>
		<gsdp_lemma>여객철도--위치한--시에--미네</gsdp_lemma>
		<head>철도역이다.</head>
		<cluster>38</cluster>
		<comment></comment>
	</sent_item>
	<sent_item id="M_T122" total_morp="25" total_word="11">
		<sent>미네 역은 일본 야마구치_현 미네 시에 위치한 서일본 여객철도 미네_선의 철도역이다.</sent>
		<sbj type="" weight="0.00" label="NP_MOD" josa="의">미네_선</sbj>
		<obj type="LCP_CITY" weight="0.18" label="NP" josa="">야마구치_현</obj>
		<gold>routeStart</gold>
		<mln_predict conf="1.000">routeStart</mln_predict>
		<cnn_predict conf="0.665">routeStart</cnn_predict>
		<gsdp>(NP_MOD)--down--NP--down--VP_MOD--down--NP_AJT--down--NP--down--(NP)</gsdp>
		<gsdp_lemma>여객철도--위치한--시에--미네</gsdp_lemma>
		<head>철도역이다.</head>
		<cluster>38</cluster>
		<comment></comment>
	</sent_item>
</sentence_list>
