<sentence_list>
	<dependency>(NP_CNJ)--up--(NP_AJT)</dependency>
	<total>1</total>
	<sent_item id="M_T2339" total_morp="38" total_word="17">
		<sent>독립운동가 겸 언론인 서재필, 갑신정변 때 사형당한 서재창과는 사돈간으로, 이들의 생가 형 서재춘의 손자 서두원은 김재순의 사위였다.</sent>
		<sbj type="PS_NAME" weight="0.60" label="NP_CNJ" josa="">서재필</sbj>
		<obj type="PS_NAME" weight="1.08" label="NP_AJT" josa="는">서재창</obj>
		<gold>relative</gold>
		<mln_predict conf="0.913">relative</mln_predict>
		<cnn_predict conf="0.861">relative</cnn_predict>
		<gsdp>(NP_CNJ)--up--(NP_AJT)</gsdp>
		<gsdp_lemma></gsdp_lemma>
		<head>사위였다.</head>
		<cluster>49</cluster>
		<comment></comment>
	</sent_item>
</sentence_list>
